{
  "startedAt": "2026-05-14T14:16:44.724Z",
  "story": "OK (5 fields)",
  "created": [],
  "updated": [
    {
      "id": 1408,
      "name": "클리닉 운영 매뉴얼"
    },
    {
      "id": 1410,
      "name": "출력·서술 규칙"
    },
    {
      "id": 1411,
      "name": "합의 안전장치"
    },
    {
      "id": 1415,
      "name": "(id 1415)"
    },
    {
      "id": 1416,
      "name": "(id 1416)"
    },
    {
      "id": 1417,
      "name": "(id 1417)"
    },
    {
      "id": 1418,
      "name": "(id 1418)"
    },
    {
      "id": 1419,
      "name": "(id 1419)"
    },
    {
      "id": 1420,
      "name": "(id 1420)"
    },
    {
      "id": 1424,
      "name": "(id 1424)"
    },
    {
      "id": 1425,
      "name": "(id 1425)"
    }
  ],
  "deleted": [],
  "errors": [],
  "finishedAt": "2026-05-14T14:16:44.800Z"
}